AUTHORS
CHANGES
LICENSE
MANIFEST.in
README.rst
setup.py
printio/__init__.py
printio/core.py
printio.egg-info/PKG-INFO
printio.egg-info/SOURCES.txt
printio.egg-info/dependency_links.txt
printio.egg-info/top_level.txt
printio/tests/__init__.py
printio/tests/test_core.py