Metadata-Version: 1.0
Name: printio
Version: 0.0.2
Summary: 
